pypeline/__init__.py
pypeline/__run.py
pypeline/bootstrap/__init__.py
pypeline/bootstrap/run.py
pypeline/domain/__init__.py
pypeline/domain/artifacts.py
pypeline/domain/config.py
pypeline/domain/execution_context.py
pypeline/domain/pipeline.py
pypeline/domain/project_slurper.py
pypeline/inputs_parser.py
pypeline/kickstart/__init__.py
pypeline/kickstart/create.py
pypeline/kickstart/templates/project/.gitignore
pypeline/kickstart/templates/project/pypeline.ps1
pypeline/kickstart/templates/project/pypeline.yaml
pypeline/kickstart/templates/project/pyproject.toml
pypeline/kickstart/templates/project/steps/my_step.py
pypeline/kickstart/templates/project/west.yaml
pypeline/main.py
pypeline/py.typed
pypeline/pypeline.py
pypeline/steps/__init__.py
pypeline/steps/create_venv.py
pypeline/steps/env_setup_script.py
pypeline/steps/scoop_install.py
pypeline/steps/west_install.py
pypeline_runner-1.26.0.dist-info/METADATA
pypeline_runner-1.26.0.dist-info/WHEEL
pypeline_runner-1.26.0.dist-info/entry_points.txt
pypeline_runner-1.26.0.dist-info/licenses/LICENSE
pypeline_runner-1.26.0.dist-info/RECORD
