Metadata-Version: 2.4
Name: pypeline-runner
Version: 1.26.0
Summary: Configure and execute pipelines with Python (similar to GitHub workflows or Jenkins pipelines).
License: MIT
License-File: LICENSE
Author: cuinixam
Author-email: me@cuinixam.com
Requires-Python: >=3.10,<4.0
Classifier: Development Status :: 2 - Pre-Alpha
Classifier: Intended Audience :: Developers
Classifier: License :: OSI Approved :: MIT License
Classifier: Natural Language :: English
Classifier: Operating System :: OS Independent
Classifier: Programming Language :: Python :: 3
Classifier: Programming Language :: Python :: 3.10
Classifier: Programming Language :: Python :: 3.11
Classifier: Programming Language :: Python :: 3.12
Classifier: Programming Language :: Python :: 3.13
Classifier: Programming Language :: Python :: 3.14
Classifier: Topic :: Software Development :: Libraries
Requires-Dist: py-app-dev (>=2.18.0,<3.0.0)
Requires-Dist: pyyaml (>=6.0.3,<7.0.0)
Requires-Dist: typer (>=0.21.1,<0.22.0)
Requires-Dist: west (>=1.5.0,<2.0.0)
Project-URL: Bug Tracker, https://github.com/cuinixam/pypeline/issues
Project-URL: Changelog, https://github.com/cuinixam/pypeline/blob/main/CHANGELOG.md
Project-URL: Documentation, https://pypeline-runner.readthedocs.io
Project-URL: Repository, https://github.com/cuinixam/pypeline
